klotan/__init__.py
klotan/exceptions.py
klotan/match.py
klotan/store.py
klotan/criteria/__init__.py
klotan/criteria/banking_criteria.py
klotan/criteria/core.py
klotan/criteria/date_criteria.py
klotan/criteria/general_criteria.py
klotan/criteria/int_criteria.py
klotan/criteria/list_criteria.py
klotan/criteria/string_criteria.py
klotan/criteria/uuid_criteria.py
klotan/criteria/web_criteria.py
klotan-1.11.0.dist-info/LICENSE
klotan-1.11.0.dist-info/METADATA
klotan-1.11.0.dist-info/WHEEL
klotan-1.11.0.dist-info/entry_points.txt
klotan-1.11.0.dist-info/top_level.txt
klotan-1.11.0.dist-info/RECORD
