Metadata-Version: 2.1
Name: klotan
Version: 1.11.0
Summary: Structural matching lib for Python
Home-page: https://sgithub.fr.world.socgen/ktollec111518/klotan
Author: SG
Author-email: 
License: UNKNOWN
Project-URL: Bug Reports, https://sgithub.fr.world.socgen/ktollec111518/klotan/issues
Project-URL: Source, https://sgithub.fr.world.socgen/ktollec111518/klotan
Keywords: matching json
Platform: UNKNOWN
Classifier: Development Status :: 3 - Alpha
Classifier: Intended Audience :: Developers
Classifier: Topic :: Software Development :: Libraries
Classifier: License :: OSI Approved :: MIT License
Classifier: Programming Language :: Python :: 3.6
Classifier: Programming Language :: Python :: 3.7
Provides-Extra: tests
Requires-Dist: pytest ; extra == 'tests'
Requires-Dist: flake8 ; extra == 'tests'
